{"nodes": [{"id": "users_derek_src_stargate_internal_ttlmap_ttlmap_go", "label": "ttlmap.go", "file_type": "code", "source_file": "/Users/derek/src/stargate/internal/ttlmap/ttlmap.go", "source_location": "L1"}, {"id": "ttlmap_options", "label": "Options", "file_type": "code", "source_file": "/Users/derek/src/stargate/internal/ttlmap/ttlmap.go", "source_location": "L18"}, {"id": "ttlmap_entry", "label": "entry", "file_type": "code", "source_file": "/Users/derek/src/stargate/internal/ttlmap/ttlmap.go", "source_location": "L31"}, {"id": "ttlmap_ttlmap", "label": "TTLMap", "file_type": "code", "source_file": "/Users/derek/src/stargate/internal/ttlmap/ttlmap.go", "source_location": "L40"}, {"id": "ttlmap_new", "label": "New()", "file_type": "code", "source_file": "/Users/derek/src/stargate/internal/ttlmap/ttlmap.go", "source_location": "L50"}, {"id": "ttlmap_ttlmap_k_v", "label": "TTLMap[K, V]", "file_type": "code", "source_file": "/Users/derek/src/stargate/internal/ttlmap/ttlmap.go", "source_location": "L68"}, {"id": "ttlmap_ttlmap_k_v_set", "label": ".Set()", "file_type": "code", "source_file": "/Users/derek/src/stargate/internal/ttlmap/ttlmap.go", "source_location": "L68"}, {"id": "ttlmap_ttlmap_k_v_evictoldest", "label": ".evictOldest()", "file_type": "code", "source_file": "/Users/derek/src/stargate/internal/ttlmap/ttlmap.go", "source_location": "L102"}, {"id": "ttlmap_ttlmap_k_v_get", "label": ".Get()", "file_type": "code", "source_file": "/Users/derek/src/stargate/internal/ttlmap/ttlmap.go", "source_location": "L127"}, {"id": "ttlmap_ttlmap_k_v_delete", "label": ".Delete()", "file_type": "code", "source_file": "/Users/derek/src/stargate/internal/ttlmap/ttlmap.go", "source_location": "L161"}, {"id": "ttlmap_ttlmap_k_v_clear", "label": ".Clear()", "file_type": "code", "source_file": "/Users/derek/src/stargate/internal/ttlmap/ttlmap.go", "source_location": "L168"}, {"id": "ttlmap_ttlmap_k_v_len", "label": ".Len()", "file_type": "code", "source_file": "/Users/derek/src/stargate/internal/ttlmap/ttlmap.go", "source_location": "L176"}, {"id": "ttlmap_ttlmap_k_v_close", "label": ".Close()", "file_type": "code", "source_file": "/Users/derek/src/stargate/internal/ttlmap/ttlmap.go", "source_location": "L194"}, {"id": "ttlmap_ttlmap_k_v_sweep", "label": ".sweep()", "file_type": "code", "source_file": "/Users/derek/src/stargate/internal/ttlmap/ttlmap.go", "source_location": "L201"}, {"id": "ttlmap_ttlmap_k_v_removeexpired", "label": ".removeExpired()", "file_type": "code", "source_file": "/Users/derek/src/stargate/internal/ttlmap/ttlmap.go", "source_location": "L218"}], "edges": [{"source": "users_derek_src_stargate_internal_ttlmap_ttlmap_go", "target": "go_pkg_context", "relation": "imports_from", "confidence": "EXTRACTED", "source_file": "/Users/derek/src/stargate/internal/ttlmap/ttlmap.go", "source_location": "L8", "weight": 1.0}, {"source": "users_derek_src_stargate_internal_ttlmap_ttlmap_go", "target": "go_pkg_sync", "relation": "imports_from", "confidence": "EXTRACTED", "source_file": "/Users/derek/src/stargate/internal/ttlmap/ttlmap.go", "source_location": "L9", "weight": 1.0}, {"source": "users_derek_src_stargate_internal_ttlmap_ttlmap_go", "target": "go_pkg_time", "relation": "imports_from", "confidence": "EXTRACTED", "source_file": "/Users/derek/src/stargate/internal/ttlmap/ttlmap.go", "source_location": "L10", "weight": 1.0}, {"source": "users_derek_src_stargate_internal_ttlmap_ttlmap_go", "target": "ttlmap_options", "relation": "contains", "confidence": "EXTRACTED", "source_file": "/Users/derek/src/stargate/internal/ttlmap/ttlmap.go", "source_location": "L18", "weight": 1.0}, {"source": "users_derek_src_stargate_internal_ttlmap_ttlmap_go", "target": "ttlmap_entry", "relation": "contains", "confidence": "EXTRACTED", "source_file": "/Users/derek/src/stargate/internal/ttlmap/ttlmap.go", "source_location": "L31", "weight": 1.0}, {"source": "users_derek_src_stargate_internal_ttlmap_ttlmap_go", "target": "ttlmap_ttlmap", "relation": "contains", "confidence": "EXTRACTED", "source_file": "/Users/derek/src/stargate/internal/ttlmap/ttlmap.go", "source_location": "L40", "weight": 1.0}, {"source": "users_derek_src_stargate_internal_ttlmap_ttlmap_go", "target": "ttlmap_new", "relation": "contains", "confidence": "EXTRACTED", "source_file": "/Users/derek/src/stargate/internal/ttlmap/ttlmap.go", "source_location": "L50", "weight": 1.0}, {"source": "ttlmap_ttlmap_k_v", "target": "ttlmap_ttlmap_k_v_set", "relation": "method", "confidence": "EXTRACTED", "source_file": "/Users/derek/src/stargate/internal/ttlmap/ttlmap.go", "source_location": "L68", "weight": 1.0}, {"source": "ttlmap_ttlmap_k_v", "target": "ttlmap_ttlmap_k_v_evictoldest", "relation": "method", "confidence": "EXTRACTED", "source_file": "/Users/derek/src/stargate/internal/ttlmap/ttlmap.go", "source_location": "L102", "weight": 1.0}, {"source": "ttlmap_ttlmap_k_v", "target": "ttlmap_ttlmap_k_v_get", "relation": "method", "confidence": "EXTRACTED", "source_file": "/Users/derek/src/stargate/internal/ttlmap/ttlmap.go", "source_location": "L127", "weight": 1.0}, {"source": "ttlmap_ttlmap_k_v", "target": "ttlmap_ttlmap_k_v_delete", "relation": "method", "confidence": "EXTRACTED", "source_file": "/Users/derek/src/stargate/internal/ttlmap/ttlmap.go", "source_location": "L161", "weight": 1.0}, {"source": "ttlmap_ttlmap_k_v", "target": "ttlmap_ttlmap_k_v_clear", "relation": "method", "confidence": "EXTRACTED", "source_file": "/Users/derek/src/stargate/internal/ttlmap/ttlmap.go", "source_location": "L168", "weight": 1.0}, {"source": "ttlmap_ttlmap_k_v", "target": "ttlmap_ttlmap_k_v_len", "relation": "method", "confidence": "EXTRACTED", "source_file": "/Users/derek/src/stargate/internal/ttlmap/ttlmap.go", "source_location": "L176", "weight": 1.0}, {"source": "ttlmap_ttlmap_k_v", "target": "ttlmap_ttlmap_k_v_close", "relation": "method", "confidence": "EXTRACTED", "source_file": "/Users/derek/src/stargate/internal/ttlmap/ttlmap.go", "source_location": "L194", "weight": 1.0}, {"source": "ttlmap_ttlmap_k_v", "target": "ttlmap_ttlmap_k_v_sweep", "relation": "method", "confidence": "EXTRACTED", "source_file": "/Users/derek/src/stargate/internal/ttlmap/ttlmap.go", "source_location": "L201", "weight": 1.0}, {"source": "ttlmap_ttlmap_k_v", "target": "ttlmap_ttlmap_k_v_removeexpired", "relation": "method", "confidence": "EXTRACTED", "source_file": "/Users/derek/src/stargate/internal/ttlmap/ttlmap.go", "source_location": "L218", "weight": 1.0}, {"source": "ttlmap_new", "target": "ttlmap_ttlmap_k_v_sweep", "relation": "calls", "confidence": "EXTRACTED", "source_file": "/Users/derek/src/stargate/internal/ttlmap/ttlmap.go", "source_location": "L61", "weight": 1.0}, {"source": "ttlmap_ttlmap_k_v_set", "target": "ttlmap_ttlmap_k_v_len", "relation": "calls", "confidence": "EXTRACTED", "source_file": "/Users/derek/src/stargate/internal/ttlmap/ttlmap.go", "source_location": "L84", "weight": 1.0}, {"source": "ttlmap_ttlmap_k_v_set", "target": "ttlmap_ttlmap_k_v_delete", "relation": "calls", "confidence": "EXTRACTED", "source_file": "/Users/derek/src/stargate/internal/ttlmap/ttlmap.go", "source_location": "L87", "weight": 1.0}, {"source": "ttlmap_ttlmap_k_v_set", "target": "ttlmap_ttlmap_k_v_evictoldest", "relation": "calls", "confidence": "EXTRACTED", "source_file": "/Users/derek/src/stargate/internal/ttlmap/ttlmap.go", "source_location": "L93", "weight": 1.0}, {"source": "ttlmap_ttlmap_k_v_evictoldest", "target": "ttlmap_ttlmap_k_v_delete", "relation": "calls", "confidence": "EXTRACTED", "source_file": "/Users/derek/src/stargate/internal/ttlmap/ttlmap.go", "source_location": "L118", "weight": 1.0}, {"source": "ttlmap_ttlmap_k_v_get", "target": "ttlmap_ttlmap_k_v_delete", "relation": "calls", "confidence": "EXTRACTED", "source_file": "/Users/derek/src/stargate/internal/ttlmap/ttlmap.go", "source_location": "L144", "weight": 1.0}, {"source": "ttlmap_ttlmap_k_v_sweep", "target": "ttlmap_ttlmap_k_v_removeexpired", "relation": "calls", "confidence": "EXTRACTED", "source_file": "/Users/derek/src/stargate/internal/ttlmap/ttlmap.go", "source_location": "L208", "weight": 1.0}, {"source": "ttlmap_ttlmap_k_v_removeexpired", "target": "ttlmap_ttlmap_k_v_delete", "relation": "calls", "confidence": "EXTRACTED", "source_file": "/Users/derek/src/stargate/internal/ttlmap/ttlmap.go", "source_location": "L225", "weight": 1.0}], "raw_calls": [{"caller_nid": "ttlmap_new", "callee": "make", "source_file": "/Users/derek/src/stargate/internal/ttlmap/ttlmap.go", "source_location": "L56"}, {"caller_nid": "ttlmap_new", "callee": "make", "source_file": "/Users/derek/src/stargate/internal/ttlmap/ttlmap.go", "source_location": "L58"}, {"caller_nid": "ttlmap_ttlmap_k_v_set", "callee": "Now", "source_file": "/Users/derek/src/stargate/internal/ttlmap/ttlmap.go", "source_location": "L69"}, {"caller_nid": "ttlmap_ttlmap_k_v_set", "callee": "Add", "source_file": "/Users/derek/src/stargate/internal/ttlmap/ttlmap.go", "source_location": "L72"}, {"caller_nid": "ttlmap_ttlmap_k_v_set", "callee": "Lock", "source_file": "/Users/derek/src/stargate/internal/ttlmap/ttlmap.go", "source_location": "L76"}, {"caller_nid": "ttlmap_ttlmap_k_v_set", "callee": "Unlock", "source_file": "/Users/derek/src/stargate/internal/ttlmap/ttlmap.go", "source_location": "L77"}, {"caller_nid": "ttlmap_ttlmap_k_v_set", "callee": "After", "source_file": "/Users/derek/src/stargate/internal/ttlmap/ttlmap.go", "source_location": "L86"}, {"caller_nid": "ttlmap_ttlmap_k_v_evictoldest", "callee": "Before", "source_file": "/Users/derek/src/stargate/internal/ttlmap/ttlmap.go", "source_location": "L110"}, {"caller_nid": "ttlmap_ttlmap_k_v_get", "callee": "RLock", "source_file": "/Users/derek/src/stargate/internal/ttlmap/ttlmap.go", "source_location": "L128"}, {"caller_nid": "ttlmap_ttlmap_k_v_get", "callee": "RUnlock", "source_file": "/Users/derek/src/stargate/internal/ttlmap/ttlmap.go", "source_location": "L130"}, {"caller_nid": "ttlmap_ttlmap_k_v_get", "callee": "After", "source_file": "/Users/derek/src/stargate/internal/ttlmap/ttlmap.go", "source_location": "L137"}, {"caller_nid": "ttlmap_ttlmap_k_v_get", "callee": "Now", "source_file": "/Users/derek/src/stargate/internal/ttlmap/ttlmap.go", "source_location": "L137"}, {"caller_nid": "ttlmap_ttlmap_k_v_get", "callee": "Lock", "source_file": "/Users/derek/src/stargate/internal/ttlmap/ttlmap.go", "source_location": "L141"}, {"caller_nid": "ttlmap_ttlmap_k_v_get", "callee": "After", "source_file": "/Users/derek/src/stargate/internal/ttlmap/ttlmap.go", "source_location": "L143"}, {"caller_nid": "ttlmap_ttlmap_k_v_get", "callee": "Now", "source_file": "/Users/derek/src/stargate/internal/ttlmap/ttlmap.go", "source_location": "L143"}, {"caller_nid": "ttlmap_ttlmap_k_v_get", "callee": "Unlock", "source_file": "/Users/derek/src/stargate/internal/ttlmap/ttlmap.go", "source_location": "L148"}, {"caller_nid": "ttlmap_ttlmap_k_v_get", "callee": "Unlock", "source_file": "/Users/derek/src/stargate/internal/ttlmap/ttlmap.go", "source_location": "L152"}, {"caller_nid": "ttlmap_ttlmap_k_v_delete", "callee": "Lock", "source_file": "/Users/derek/src/stargate/internal/ttlmap/ttlmap.go", "source_location": "L162"}, {"caller_nid": "ttlmap_ttlmap_k_v_delete", "callee": "delete", "source_file": "/Users/derek/src/stargate/internal/ttlmap/ttlmap.go", "source_location": "L163"}, {"caller_nid": "ttlmap_ttlmap_k_v_delete", "callee": "Unlock", "source_file": "/Users/derek/src/stargate/internal/ttlmap/ttlmap.go", "source_location": "L164"}, {"caller_nid": "ttlmap_ttlmap_k_v_clear", "callee": "Lock", "source_file": "/Users/derek/src/stargate/internal/ttlmap/ttlmap.go", "source_location": "L169"}, {"caller_nid": "ttlmap_ttlmap_k_v_clear", "callee": "make", "source_file": "/Users/derek/src/stargate/internal/ttlmap/ttlmap.go", "source_location": "L170"}, {"caller_nid": "ttlmap_ttlmap_k_v_clear", "callee": "Unlock", "source_file": "/Users/derek/src/stargate/internal/ttlmap/ttlmap.go", "source_location": "L171"}, {"caller_nid": "ttlmap_ttlmap_k_v_len", "callee": "Now", "source_file": "/Users/derek/src/stargate/internal/ttlmap/ttlmap.go", "source_location": "L177"}, {"caller_nid": "ttlmap_ttlmap_k_v_len", "callee": "RLock", "source_file": "/Users/derek/src/stargate/internal/ttlmap/ttlmap.go", "source_location": "L178"}, {"caller_nid": "ttlmap_ttlmap_k_v_len", "callee": "RUnlock", "source_file": "/Users/derek/src/stargate/internal/ttlmap/ttlmap.go", "source_location": "L179"}, {"caller_nid": "ttlmap_ttlmap_k_v_len", "callee": "After", "source_file": "/Users/derek/src/stargate/internal/ttlmap/ttlmap.go", "source_location": "L183"}, {"caller_nid": "ttlmap_ttlmap_k_v_close", "callee": "Do", "source_file": "/Users/derek/src/stargate/internal/ttlmap/ttlmap.go", "source_location": "L195"}, {"caller_nid": "ttlmap_ttlmap_k_v_close", "callee": "close", "source_file": "/Users/derek/src/stargate/internal/ttlmap/ttlmap.go", "source_location": "L196"}, {"caller_nid": "ttlmap_ttlmap_k_v_sweep", "callee": "NewTicker", "source_file": "/Users/derek/src/stargate/internal/ttlmap/ttlmap.go", "source_location": "L202"}, {"caller_nid": "ttlmap_ttlmap_k_v_sweep", "callee": "Stop", "source_file": "/Users/derek/src/stargate/internal/ttlmap/ttlmap.go", "source_location": "L203"}, {"caller_nid": "ttlmap_ttlmap_k_v_sweep", "callee": "Done", "source_file": "/Users/derek/src/stargate/internal/ttlmap/ttlmap.go", "source_location": "L209"}, {"caller_nid": "ttlmap_ttlmap_k_v_removeexpired", "callee": "Now", "source_file": "/Users/derek/src/stargate/internal/ttlmap/ttlmap.go", "source_location": "L219"}, {"caller_nid": "ttlmap_ttlmap_k_v_removeexpired", "callee": "Lock", "source_file": "/Users/derek/src/stargate/internal/ttlmap/ttlmap.go", "source_location": "L220"}, {"caller_nid": "ttlmap_ttlmap_k_v_removeexpired", "callee": "Unlock", "source_file": "/Users/derek/src/stargate/internal/ttlmap/ttlmap.go", "source_location": "L221"}, {"caller_nid": "ttlmap_ttlmap_k_v_removeexpired", "callee": "After", "source_file": "/Users/derek/src/stargate/internal/ttlmap/ttlmap.go", "source_location": "L224"}]}